CMakeLists.txt
LICENSE
MANIFEST.in
README.md
pyproject.toml
requirements-common.txt
requirements-cuda.txt
setup.py
cmake/cpu_extension.cmake
cmake/hipify.py
cmake/utils.cmake
csrc/activation_kernels.cu
csrc/cache.h
csrc/cache_kernels.cu
csrc/cuda_compat.h
csrc/cuda_utils.h
csrc/cuda_utils_kernels.cu
csrc/custom_all_reduce.cu
csrc/custom_all_reduce.cuh
csrc/custom_all_reduce_test.cu
csrc/dispatch_utils.h
csrc/layernorm_kernels.cu
csrc/moe_align_block_size_kernels.cu
csrc/ops.h
csrc/pos_encoding_kernels.cu
csrc/pybind.cpp
csrc/reduction_utils.cuh
csrc/attention/attention_dtypes.h
csrc/attention/attention_generic.cuh
csrc/attention/attention_kernels.cu
csrc/attention/attention_utils.cuh
csrc/attention/dtype_bfloat16.cuh
csrc/attention/dtype_float16.cuh
csrc/attention/dtype_float32.cuh
csrc/attention/dtype_fp8.cuh
csrc/cpu/activation.cpp
csrc/cpu/attention.cpp
csrc/cpu/cache.cpp
csrc/cpu/cpu_types.hpp
csrc/cpu/layernorm.cpp
csrc/cpu/pos_encoding.cpp
csrc/cpu/pybind.cpp
csrc/moe/moe_ops.cpp
csrc/moe/moe_ops.h
csrc/moe/topk_softmax_kernels.cu
csrc/punica/LICENSE
csrc/punica/punica_ops.cc
csrc/punica/bgmv/bgmv_bf16_bf16_bf16.cu
csrc/punica/bgmv/bgmv_bf16_fp32_bf16.cu
csrc/punica/bgmv/bgmv_config.h
csrc/punica/bgmv/bgmv_fp16_fp16_fp16.cu
csrc/punica/bgmv/bgmv_fp16_fp32_fp16.cu
csrc/punica/bgmv/bgmv_fp32_bf16_bf16.cu
csrc/punica/bgmv/bgmv_fp32_fp16_fp16.cu
csrc/punica/bgmv/bgmv_impl.cuh
csrc/punica/bgmv/generator.py
csrc/punica/bgmv/vec_dtypes.cuh
csrc/quantization/aqlm/gemm_kernels.cu
csrc/quantization/awq/dequantize.cuh
csrc/quantization/awq/gemm_kernels.cu
csrc/quantization/fp8/fp8_cuda_kernels.cu
csrc/quantization/fp8/amd_detail/hip_float8.h
csrc/quantization/fp8/amd_detail/hip_float8_impl.h
csrc/quantization/fp8/amd_detail/quant_utils.cuh
csrc/quantization/fp8_e5m2_kvcache/quant_utils.cuh
csrc/quantization/gptq/compat.cuh
csrc/quantization/gptq/matrix_view.cuh
csrc/quantization/gptq/q_gemm.cu
csrc/quantization/gptq/qdq_2.cuh
csrc/quantization/gptq/qdq_3.cuh
vllm_online.egg-info/PKG-INFO
vllm_online.egg-info/SOURCES.txt
vllm_online.egg-info/dependency_links.txt
vllm_online.egg-info/requires.txt
vllm_online.egg-info/top_level.txt