Metadata-Version: 2.1
Name: vllm-online
Version: 0.4.1
Summary: A high-throughput and memory-efficient inference and serving engine for LLMs
Home-page: https://github.com/vllm-project/vllm
Author: vLLM Team
License: Apache 2.0
Project-URL: Homepage, https://github.com/vllm-project/vllm
Project-URL: Documentation, https://vllm.readthedocs.io/en/latest/
Classifier: Programming Language :: Python :: 3.8
Classifier: Programming Language :: Python :: 3.9
Classifier: Programming Language :: Python :: 3.10
Classifier: Programming Language :: Python :: 3.11
Classifier: License :: OSI Approved :: Apache Software License
Classifier: Topic :: Scientific/Engineering :: Artificial Intelligence
Requires-Python: >=3.8
Provides-Extra: tensorizer
License-File: LICENSE
